Digital Design/Lab 6/Q2/Q2.srcs/sources_1/new/dffb.v
`timescale 1ns / 1ps
// Code your design here
module dffb (q, d, clk, rst,q1);
 output q,q1;
 input d, clk, rst;
 reg q,q1;
 always @(posedge clk)
   if (rst) q = 1'b0;           //DFF using Blocking statements:
 else 
   begin
  q <= d;           //DFF using Non- Blocking statements:
  q1 <= q;          
   end
endmodule

Digital Design/Lab 6/Q2/Q2.srcs/sources_1/new/D_FF_testbench.v
`timescale 1ns / 1ps
// Code your testbench here
// or browse Examples
module D_FF_testbench;
reg CLK, reset, d;
wire q,q1;
parameter PERIOD = 1000;
  dffb m1(.q(q),.q1(q1),.d(d),.rst(reset),.clk(CLK)); // Instantiate the D_FF
initial CLK <= 0; // Set up clock
  always #1 CLK<= ~CLK;
initial begin // Set up signals
d = 0; 
#1 d =1;
#5 d=0;
#2 d=1;
#1 d =1;
#5 d=0;
#2 d=1;
#1 d =1;
#5 d=0;
#2 d=1;
#1 d =1;
#5 d=0;
#2 d=1;
#1 d =1;
#5 d=0;
#2 d=1;
#1 d =1;
#5 d=0;
#2 d=1;
#1 d =1;
#5 d=0;
#2 d=1;
#1 d =1;
#5 d=0;
#2 d=1;  
#1000 $finish;  
end
  
  initial begin
    // Dump waves
    $dumpfile("dump.vcd");
    $dumpvars(1);
  end
endmodule

Digital Design/Lab 6/Q2/Q2.sim/sim_1/behav/xsim/dump.vcd
$date
   Fri Mar  4 17:57:02 2022
$end
$version
  2018.3
$end
$timescale
  1ps
$end
$scope module D_FF_testbench $end
$var reg 1 ! CLK $end
$var reg 1 " reset $end
$var reg 1 # d $end
$var wire 1 $ q $end
$var wire 1 % q1 $end
$var parameter 32 & PERIOD [31:0] $end
$upscope $end
$enddefinitions $end
#0
$dumpvars
0!
x"
0#
x$
x%
b1111101000 &
$end
#1000
1!
1#
1$
#2000
0!
#3000
1!
1%
#4000
0!
#5000
1!
#6000
0!
0#
#7000
1!
0$
#8000
0!
1#
#9000
1!
1$
0%
#10000
0!
#11000
1!
1%
#12000
0!
#13000
1!
#14000
0!
0#
#15000
1!
0$
#16000
0!
1#
#17000
1!
1$
0%
#18000
0!
#19000
1!
1%
#20000
0!
#21000
1!
#22000
0!
0#
#23000
1!
0$
#24000
0!
1#
#25000
1!
1$
0%
#26000
0!
#27000
1!
1%
#28000
0!
#29000
1!
#30000
0!
0#
#31000
1!
0$
#32000
0!
1#
#33000
1!
1$
0%
#34000
0!
#35000
1!
1%
#36000
0!
#37000
1!
#38000
0!
0#
#39000
1!
0$
#40000
0!
1#
#41000
1!
1$
0%
#42000
0!
#43000
1!
1%
#44000
0!
#45000
1!
#46000
0!
0#
#47000
1!
0$
#48000
0!
1#
#49000
1!
1$
0%
#50000
0!
#51000
1!
1%
#52000
0!
#53000
1!
#54000
0!
0#
#55000
1!
0$
#56000
0!
1#
#57000
1!
1$
0%
#58000
0!
#59000
1!
1%
#60000
0!
#61000
1!
#62000
0!
0#
#63000
1!
0$
#64000
0!
1#
#65000
1!
1$
0%
#66000
0!
#67000
1!
1%
